{
	"configurations" : 
	[
		{
			"directories" : 
			[
				{
					"build" : ".",
					"jsonFile" : "directory-.-Debug-f5ebdc15457944623624.json",
					"minimumCMakeVersion" : 
					{
						"string" : "3.27"
					},
					"projectIndex" : 0,
					"source" : ".",
					"targetIndexes" : 
					[
						0
					]
				}
			],
			"name" : "Debug",
			"projects" : 
			[
				{
					"directoryIndexes" : 
					[
						0
					],
					"name" : "Wyklad",
					"targetIndexes" : 
					[
						0
					]
				}
			],
			"targets" : 
			[
				{
					"directoryIndex" : 0,
					"id" : "Wyklad::@6890427a1f51a3e7e1df",
					"jsonFile" : "target-Wyklad-Debug-e36f4d60582b8050c8b3.json",
					"name" : "Wyklad",
					"projectIndex" : 0
				}
			]
		}
	],
	"kind" : "codemodel",
	"paths" : 
	{
		"build" : "/Users/arturcegielka-posluszny/CLionProjects/Wyklad/cmake-build-debug",
		"source" : "/Users/arturcegielka-posluszny/CLionProjects/Wyklad"
	},
	"version" : 
	{
		"major" : 2,
		"minor" : 6
	}
}
